dafne_dl/DynamicDLModel.py
dafne_dl/LocalModelProvider.py
dafne_dl/MixedModelProvider.py
dafne_dl/RemoteModelProvider.py
dafne_dl/__init__.py
dafne_dl/interfaces.py
dafne_dl/misc.py
dafne_dl/common/DataGenerators.py
dafne_dl/common/__init__.py
dafne_dl/common/biascorrection.py
dafne_dl/common/padorcut.py
dafne_dl/common/preprocess_train.py
dafne_dl/labels/__init__.py
dafne_dl/labels/leg.py
dafne_dl/labels/thigh.py
dafne_dl/labels/utils.py
dafne_dl/resources/__init__.py
dafne_dl/resources/runtime_dependencies.cfg
dafne_dl-1.4a3.dist-info/COPYING
dafne_dl-1.4a3.dist-info/COPYING.LESSER
dafne_dl-1.4a3.dist-info/METADATA
dafne_dl-1.4a3.dist-info/WHEEL
dafne_dl-1.4a3.dist-info/top_level.txt
dafne_dl-1.4a3.dist-info/RECORD
