Metadata-Version: 2.1
Name: dafne-dl
Version: 1.4a3
Summary: Deep Learning module for Dafne
Home-page: https://github.com/dafne-imaging/dafne-dl
Author: Francesco Santini
Author-email: francesco.santini@unibas.ch
Project-URL: Bug Tracker, https://github.com/dafne-imaging/dafne-dl/issues
Classifier: Programming Language :: Python :: 3
Classifier: License :: OSI Approved :: GNU Lesser General Public License v3 or later (LGPLv3+)
Classifier: Operating System :: OS Independent
Requires-Python: >=3.6
License-File: COPYING
License-File: COPYING.LESSER
Requires-Dist: numpy
Requires-Dist: scikit-image
Requires-Dist: scipy
Requires-Dist: dill
Requires-Dist: requests
Requires-Dist: flexidep
Requires-Dist: importlib-resources ; python_version < "3.10"
